spode
