Metadata-Version: 2.1
Name: spode
Version: 0.0.8
Summary: A simulator with programmable photonics and differentiability emphasis
Home-page: https://github.com/zhengqigao/spode
Author: ZhengqiGao
Author-email: zhenqi@mit.edu
License: GPL-3.0
Platform: UNKNOWN
Requires-Python: >=3
